[{"date":"2024-01-04T11","id":"18y8r41","position":58,"score":957,"subreddit_display_name":"UkraineWarVideoReport","subreddit_id":"5wjmo8","title":"Vadim gets emotional explaining his life in Russia","is_self":0,"url":"https://v.redd.it/aiepx2iy1eac1","upvote_ratio":0.97999999999999998223,"num_comments":84,"created":1704359015,"created_date":"2024-01-04T09:03:35+0000"},
{"date":"2024-01-04T11","id":"18y8pq7","position":4,"score":3940,"subreddit_display_name":"MadeMeSmile","subreddit_id":"2uqcm","title":"Parents watching their kid take his first steps","is_self":0,"url":"https://v.redd.it/tc077dox1eac1","upvote_ratio":0.98999999999999999111,"num_comments":98,"created":1704358869,"created_date":"2024-01-04T09:01:09+0000"},
{"date":"2024-01-04T11","id":"18y7vj7","position":67,"score":1059,"subreddit_display_name":"Genshin_Impact_Leaks","subreddit_id":"3l2acu","title":"4.3 Phase 2 Character and Weapon Banners","is_self":0,"url":"https://www.reddit.com/gallery/18y7vj7","upvote_ratio":0.95999999999999996447,"num_comments":298,"created":1704355409,"created_date":"2024-01-04T08:03:29+0000"},
{"date":"2024-01-04T11","id":"18y7qqf","position":42,"score":1485,"subreddit_display_name":"HolUp","subreddit_id":"qir9n","title":"hahhha","is_self":0,"url":"https://v.redd.it/4wid3ei2qdac1","upvote_ratio":0.84999999999999997779,"num_comments":86,"created":1704354888,"created_date":"2024-01-04T07:54:48+0000"},
{"date":"2024-01-04T11","id":"18y76e6","position":23,"score":2185,"subreddit_display_name":"comics","subreddit_id":"2qh0s","title":"I'm sick today","is_self":0,"url":"https://i.redd.it/m66awibejdac1.png","upvote_ratio":0.97999999999999998223,"num_comments":19,"created":1704352652,"created_date":"2024-01-04T07:17:32+0000"},
{"date":"2024-01-04T11","id":"18y75oi","position":14,"score":3631,"subreddit_display_name":"dankmemes","subreddit_id":"2zmfe","title":"what","is_self":0,"url":"https://i.redd.it/169oplh8jdac1.gif","upvote_ratio":0.94999999999999995559,"num_comments":165,"created":1704352572,"created_date":"2024-01-04T07:16:12+0000"},
{"date":"2024-01-04T11","id":"18y73t5","position":22,"score":2486,"subreddit_display_name":"Awww","subreddit_id":"2suml","title":"Adorable Prank by a Clever Pup","is_self":0,"url":"https://v.redd.it/lh1mlgwlidac1","upvote_ratio":0.97999999999999998223,"num_comments":20,"created":1704352374,"created_date":"2024-01-04T07:12:54+0000"},
{"date":"2024-01-04T11","id":"18y6guf","position":63,"score":1452,"subreddit_display_name":"Genshin_Impact","subreddit_id":"12p4l2","title":"Are you kidding me","is_self":0,"url":"https://www.reddit.com/gallery/18y6guf","upvote_ratio":0.92000000000000003996,"num_comments":168,"created":1704349932,"created_date":"2024-01-04T06:32:12+0000"},
{"date":"2024-01-04T11","id":"18y658r","position":8,"score":5679,"subreddit_display_name":"pcmasterrace","subreddit_id":"2sgp1","title":"Edge's pdf reader is best I've ever seen.","is_self":0,"url":"https://i.redd.it/9lo2c1id7dac1.png","upvote_ratio":0.94999999999999995559,"num_comments":346,"created":1704348765,"created_date":"2024-01-04T06:12:45+0000"},
{"date":"2024-01-04T11","id":"18y61ks","position":33,"score":5355,"subreddit_display_name":"meirl","subreddit_id":"2s5ti","title":"Meirl","is_self":0,"url":"https://i.redd.it/h94hhzct6dac1.jpeg","upvote_ratio":0.97999999999999998223,"num_comments":68,"created":1704348411,"created_date":"2024-01-04T06:06:51+0000"},
{"date":"2024-01-04T11","id":"18y5zjt","position":57,"score":1665,"subreddit_display_name":"MinecraftMemes","subreddit_id":"2sq0h","title":"...","is_self":0,"url":"https://i.redd.it/pvlmqvma6dac1.jpeg","upvote_ratio":0.94999999999999995559,"num_comments":103,"created":1704348218,"created_date":"2024-01-04T06:03:38+0000"},
{"date":"2024-01-04T11","id":"18y5v80","position":1,"score":14763,"subreddit_display_name":"ProgrammerHumor","subreddit_id":"2tex6","title":"programmingPeaked","is_self":0,"url":"https://i.redd.it/s2dimkb55dac1.jpeg","upvote_ratio":0.96999999999999997335,"num_comments":325,"created":1704347833,"created_date":"2024-01-04T05:57:13+0000"},
{"date":"2024-01-04T11","id":"18y5rii","position":15,"score":3959,"subreddit_display_name":"Steam","subreddit_id":"2qwis","title":"Show me a single person who voted RDR2","is_self":0,"url":"https://i.redd.it/639ams414dac1.png","upvote_ratio":0.9399999999999999467,"num_comments":308,"created":1704347479,"created_date":"2024-01-04T05:51:19+0000"},
{"date":"2024-01-04T11","id":"18y5nu7","position":9,"score":6657,"subreddit_display_name":"BatmanArkham","subreddit_id":"2y9q4","title":"Our insanity has reached there","is_self":0,"url":"https://i.redd.it/tdtbv9n33dac1.png","upvote_ratio":0.94999999999999995559,"num_comments":104,"created":1704347145,"created_date":"2024-01-04T05:45:45+0000"},
{"date":"2024-01-04T11","id":"18y5huf","position":10,"score":7528,"subreddit_display_name":"memes","subreddit_id":"2qjpg","title":"Crawls back into my Shell","is_self":0,"url":"https://i.redd.it/qttb6gzh1dac1.jpeg","upvote_ratio":0.82999999999999996003,"num_comments":845,"created":1704346607,"created_date":"2024-01-04T05:36:47+0000"},
{"date":"2024-01-04T11","id":"18y530y","position":68,"score":1782,"subreddit_display_name":"batman","subreddit_id":"2qqt8","title":"Maybe he would actually be a good Batman","is_self":0,"url":"https://v.redd.it/81hncbnfxcac1","upvote_ratio":0.9399999999999999467,"num_comments":199,"created":1704345253,"created_date":"2024-01-04T05:14:13+0000"},
{"date":"2024-01-04T11","id":"18y51tj","position":3,"score":13173,"subreddit_display_name":"wholesomememes","subreddit_id":"3gcwj","title":"healthy thinking","is_self":0,"url":"https://i.redd.it/6chzygf9wcac1.png","upvote_ratio":0.94999999999999995559,"num_comments":630,"created":1704345142,"created_date":"2024-01-04T05:12:22+0000"},
{"date":"2024-01-04T11","id":"18y506p","position":40,"score":2568,"subreddit_display_name":"me_irl","subreddit_id":"2vegg","title":"me_irl","is_self":0,"url":"https://v.redd.it/v34sc8aqwcac1","upvote_ratio":0.95999999999999996447,"num_comments":32,"created":1704345004,"created_date":"2024-01-04T05:10:04+0000"},
{"date":"2024-01-04T11","id":"18y4zq1","position":2,"score":14299,"subreddit_display_name":"meirl","subreddit_id":"2s5ti","title":"meirl","is_self":0,"url":"https://v.redd.it/mtgp5y3mwcac1","upvote_ratio":0.94999999999999995559,"num_comments":191,"created":1704344965,"created_date":"2024-01-04T05:09:25+0000"},
{"date":"2024-01-04T11","id":"18y4ze4","position":54,"score":2082,"subreddit_display_name":"Hololive","subreddit_id":"29numb","title":"Do I return the other one?","is_self":0,"url":"https://i.redd.it/toz8v3jhwcac1.png","upvote_ratio":0.98999999999999999111,"num_comments":24,"created":1704344935,"created_date":"2024-01-04T05:08:55+0000"},
{"date":"2024-01-04T11","id":"18y4rfo","position":6,"score":9351,"subreddit_display_name":"Damnthatsinteresting","subreddit_id":"2xxyj","title":"Tsunami in the making","is_self":0,"url":"https://v.redd.it/snqu8fhducac1","upvote_ratio":0.95999999999999996447,"num_comments":287,"created":1704344232,"created_date":"2024-01-04T04:57:12+0000"},
{"date":"2024-01-04T11","id":"18y4pl4","position":7,"score":8105,"subreddit_display_name":"Eyebleach","subreddit_id":"2s427","title":"ᵂᵉᵉᵉᵉ","is_self":0,"url":"https://i.imgur.com/7AJi4eR.gifv","upvote_ratio":0.97999999999999998223,"num_comments":60,"created":1704344064,"created_date":"2024-01-04T04:54:24+0000"},
{"date":"2024-01-04T11","id":"18y4oxn","position":38,"score":2826,"subreddit_display_name":"CrazyFuckingVideos","subreddit_id":"45hae8","title":"IRL streamer swatted while drunk streaming, he's so out of it he has no idea what is going on","is_self":0,"url":"https://v.redd.it/yvzq2jgrtcac1","upvote_ratio":0.94999999999999995559,"num_comments":299,"created":1704344004,"created_date":"2024-01-04T04:53:24+0000"},
{"date":"2024-01-04T11","id":"18y4lhi","position":90,"score":1596,"subreddit_display_name":"meme","subreddit_id":"2qi1r","title":"Good teacher","is_self":0,"url":"https://i.redd.it/rq9nou6vscac1.png","upvote_ratio":0.97999999999999998223,"num_comments":5,"created":1704343709,"created_date":"2024-01-04T04:48:29+0000"},
{"date":"2024-01-04T11","id":"18y4fm2","position":26,"score":3389,"subreddit_display_name":"technology","subreddit_id":"2qh16","title":"Starbucks accused of rigging payments in app for nearly $900 million gain over 5 years by consumer watchdog group","is_self":0,"url":"https://fortune.com/2024/01/03/starbucks-app-dark-side-unspent-payments-900-million-5-years/","upvote_ratio":0.95999999999999996447,"num_comments":200,"created":1704343195,"created_date":"2024-01-04T04:39:55+0000"},
{"date":"2024-01-04T11","id":"18y4dg1","position":43,"score":7770,"subreddit_display_name":"memes","subreddit_id":"2qjpg","title":"He was on the list, apparently.","is_self":0,"url":"https://i.redd.it/ykz3brvqqcac1.gif","upvote_ratio":0.95999999999999996447,"num_comments":187,"created":1704342990,"created_date":"2024-01-04T04:36:30+0000"},
{"date":"2024-01-04T11","id":"18y46qm","position":73,"score":2007,"subreddit_display_name":"ChainsawMan","subreddit_id":"rmtrq","title":"Congrats","is_self":0,"url":"https://i.redd.it/11bd82jzocac1.jpeg","upvote_ratio":0.96999999999999997335,"num_comments":55,"created":1704342399,"created_date":"2024-01-04T04:26:39+0000"},
{"date":"2024-01-04T11","id":"18y423v","position":94,"score":3655,"subreddit_display_name":"facepalm","subreddit_id":"2r5rp","title":"Fun fact: This isnt true","is_self":0,"url":"https://i.redd.it/6w24bc3rncac1.png","upvote_ratio":0.9399999999999999467,"num_comments":339,"created":1704342007,"created_date":"2024-01-04T04:20:07+0000"},
{"date":"2024-01-04T11","id":"18y3znw","position":99,"score":1592,"subreddit_display_name":"reddeadredemption","subreddit_id":"2rn7o","title":"Guys, I think I’ve outdone myself this time","is_self":0,"url":"https://www.reddit.com/gallery/18y3znw","upvote_ratio":0.95999999999999996447,"num_comments":86,"created":1704341803,"created_date":"2024-01-04T04:16:43+0000"},
{"date":"2024-01-04T11","id":"18y3vtu","position":21,"score":5074,"subreddit_display_name":"therewasanattempt","subreddit_id":"39ne7","title":"To mind your own business","is_self":0,"url":"https://v.redd.it/29iy6j19mcac1","upvote_ratio":0.85999999999999998667,"num_comments":143,"created":1704341478,"created_date":"2024-01-04T04:11:18+0000"},
{"date":"2024-01-04T11","id":"18y3loi","position":75,"score":2235,"subreddit_display_name":"teenagers","subreddit_id":"2rjli","title":"My dad bought me this for Christmas…","is_self":0,"url":"https://i.redd.it/j727940rjcac1.jpeg","upvote_ratio":0.95999999999999996447,"num_comments":248,"created":1704340639,"created_date":"2024-01-04T03:57:19+0000"},
{"date":"2024-01-04T11","id":"18y3cev","position":52,"score":2649,"subreddit_display_name":"nba","subreddit_id":"2qo4s","title":"[Highlight] Jalen Duren dunks on Walker Kessler then gets on his shoulders for a piggyback ride","is_self":0,"url":"https://streamable.com/91wpjl","upvote_ratio":0.96999999999999997335,"num_comments":234,"created":1704339876,"created_date":"2024-01-04T03:44:36+0000"},
{"date":"2024-01-04T11","id":"18y3ab7","position":36,"score":3626,"subreddit_display_name":"JustGuysBeingDudes","subreddit_id":"33rtj6","title":"Care for a puff of color boys?","is_self":0,"url":"https://v.redd.it/ezeacfiwgcac1","upvote_ratio":0.93000000000000004884,"num_comments":119,"created":1704339699,"created_date":"2024-01-04T03:41:39+0000"},
{"date":"2024-01-04T11","id":"18y378h","position":5,"score":19772,"subreddit_display_name":"Unexpected","subreddit_id":"2w67q","title":"Everyone loves her present","is_self":0,"url":"https://v.redd.it/1f60z2y4gcac1","upvote_ratio":0.9399999999999999467,"num_comments":520,"created":1704339434,"created_date":"2024-01-04T03:37:14+0000"},
{"date":"2024-01-04T11","id":"18y337s","position":13,"score":8705,"subreddit_display_name":"mildlyinfuriating","subreddit_id":"2ubgg","title":"I had a dentist fart in my face today.","is_self":1,"url":"https://www.reddit.com/r/mildlyinfuriating/comments/18y337s/i_had_a_dentist_fart_in_my_face_today/","upvote_ratio":0.9399999999999999467,"num_comments":690,"created":1704339098,"created_date":"2024-01-04T03:31:38+0000"},
{"date":"2024-01-04T11","id":"18y31ml","position":17,"score":6870,"subreddit_display_name":"tumblr","subreddit_id":"2r7hk","title":"ngl I feel like Dio would be a fun coworker to have","is_self":0,"url":"https://i.redd.it/1h1lcmnrecac1.jpeg","upvote_ratio":0.95999999999999996447,"num_comments":87,"created":1704338978,"created_date":"2024-01-04T03:29:38+0000"},
{"date":"2024-01-04T11","id":"18y30pt","position":56,"score":2857,"subreddit_display_name":"Terraria","subreddit_id":"2sg5b","title":"Some humanized bosses ft. the ladies :D","is_self":0,"url":"https://www.reddit.com/gallery/18y30pt","upvote_ratio":0.9399999999999999467,"num_comments":208,"created":1704338900,"created_date":"2024-01-04T03:28:20+0000"},
{"date":"2024-01-04T11","id":"18y2ybt","position":60,"score":2643,"subreddit_display_name":"funny","subreddit_id":"2qh33","title":"The way mom looking at its child😂","is_self":0,"url":"https://v.redd.it/tm5m4pjzdcac1","upvote_ratio":0.88000000000000000444,"num_comments":147,"created":1704338704,"created_date":"2024-01-04T03:25:04+0000"},
{"date":"2024-01-04T11","id":"18y2qe5","position":18,"score":5946,"subreddit_display_name":"todayilearned","subreddit_id":"2qqjc","title":"TIL That the dried up white dog poop common before the '90s was due to dog food containing too much calcium and bone meal.","is_self":0,"url":"https://www.iflscience.com/why-was-white-dog-poop-so-common-before-the-90s-66581","upvote_ratio":0.96999999999999997335,"num_comments":223,"created":1704338071,"created_date":"2024-01-04T03:14:31+0000"},
{"date":"2024-01-04T11","id":"18y2h2e","position":88,"score":2224,"subreddit_display_name":"malelivingspace","subreddit_id":"2v70p","title":"Office set up when I’m too tired to commute","is_self":0,"url":"https://i.redd.it/hazdz2wp9cac1.jpeg","upvote_ratio":0.93000000000000004884,"num_comments":269,"created":1704337315,"created_date":"2024-01-04T03:01:55+0000"},
{"date":"2024-01-04T11","id":"18y291u","position":11,"score":9770,"subreddit_display_name":"nottheonion","subreddit_id":"2qnts","title":"'Rich Dad, Poor Dad' Robert Kiyosaki says he's $1.2 billion in debt because 'if I go bankrupt, the bank goes bankrupt.' not my problem'","is_self":0,"url":"https://biz.crast.net/rich-dad-poor-dad-robert-kiyosaki-says-hes-1-2-billion-in-debt-because-if-i-go-bankrupt-the-bank-goes-bankrupt-not-my-problem/","upvote_ratio":0.94999999999999995559,"num_comments":705,"created":1704336683,"created_date":"2024-01-04T02:51:23+0000"},
{"date":"2024-01-04T11","id":"18y25u9","position":70,"score":2813,"subreddit_display_name":"AITAH","subreddit_id":"446kys","title":"AITAH for calling my Father in law a bastard after he pressured us into getting a paternity test.","is_self":1,"url":"https://www.reddit.com/r/AITAH/comments/18y25u9/aitah_for_calling_my_father_in_law_a_bastard/","upvote_ratio":0.93000000000000004884,"num_comments":306,"created":1704336433,"created_date":"2024-01-04T02:47:13+0000"},
{"date":"2024-01-04T11","id":"18y22ma","position":16,"score":7868,"subreddit_display_name":"NonPoliticalTwitter","subreddit_id":"39gt6y","title":"Y2K","is_self":0,"url":"https://i.redd.it/skvz6ieh6cac1.jpeg","upvote_ratio":0.95999999999999996447,"num_comments":87,"created":1704336175,"created_date":"2024-01-04T02:42:55+0000"},
{"date":"2024-01-04T11","id":"18y22j6","position":84,"score":2490,"subreddit_display_name":"SweatyPalms","subreddit_id":"2v567","title":"This is dangerous as fuck","is_self":0,"url":"https://v.redd.it/neutpgag6cac1","upvote_ratio":0.91000000000000003108,"num_comments":299,"created":1704336167,"created_date":"2024-01-04T02:42:47+0000"},
{"date":"2024-01-04T11","id":"18y1xch","position":98,"score":4771,"subreddit_display_name":"mildlyinteresting","subreddit_id":"2ti4h","title":"The fake phone number I use to get a grocery discount already has saved people $1471.79 this year","is_self":0,"url":"https://i.redd.it/7g7v41t25cac1.jpeg","upvote_ratio":0.96999999999999997335,"num_comments":223,"created":1704335765,"created_date":"2024-01-04T02:36:05+0000"},
{"date":"2024-01-04T11","id":"18y1mox","position":55,"score":3600,"subreddit_display_name":"theydidthemath","subreddit_id":"2x23b","title":"[REQUEST] How small would the earth have to be for the bottom to be true?","is_self":0,"url":"https://i.redd.it/1sc3c7xt2cac1.jpeg","upvote_ratio":0.94999999999999995559,"num_comments":187,"created":1704334947,"created_date":"2024-01-04T02:22:27+0000"},
{"date":"2024-01-04T11","id":"18y1gxn","position":12,"score":17287,"subreddit_display_name":"facepalm","subreddit_id":"2r5rp","title":"Keep it simple stupid","is_self":0,"url":"https://i.redd.it/4wtyo5vg1cac1.jpeg","upvote_ratio":0.92000000000000003996,"num_comments":916,"created":1704334500,"created_date":"2024-01-04T02:15:00+0000"},
{"date":"2024-01-04T11","id":"18y1d2b","position":86,"score":6319,"subreddit_display_name":"Awww","subreddit_id":"2suml","title":"Swan couple reunited after one was treated for sickness.","is_self":0,"url":"https://v.redd.it/5gk5wp6i0cac1","upvote_ratio":0.96999999999999997335,"num_comments":93,"created":1704334208,"created_date":"2024-01-04T02:10:08+0000"},
{"date":"2024-01-04T11","id":"18y10x1","position":35,"score":5199,"subreddit_display_name":"aww","subreddit_id":"2qh1o","title":"My boy will be 20 this year, and he's still majestic AF","is_self":0,"url":"https://www.reddit.com/gallery/18y10x1","upvote_ratio":0.95999999999999996447,"num_comments":90,"created":1704333308,"created_date":"2024-01-04T01:55:08+0000"},
{"date":"2024-01-04T11","id":"18y0r7x","position":50,"score":4225,"subreddit_display_name":"oddlyspecific","subreddit_id":"2wjlc","title":"Time to grab the pitchforks.","is_self":0,"url":"https://i.redd.it/7r1ffo6svbac1.jpeg","upvote_ratio":0.93000000000000004884,"num_comments":727,"created":1704332576,"created_date":"2024-01-04T01:42:56+0000"},
{"date":"2024-01-04T11","id":"18y0nfc","position":66,"score":9558,"subreddit_display_name":"Unexpected","subreddit_id":"2w67q","title":"Professional pouring job","is_self":0,"url":"https://v.redd.it/imtssqvtubac1","upvote_ratio":0.95999999999999996447,"num_comments":178,"created":1704332291,"created_date":"2024-01-04T01:38:11+0000"},
{"date":"2024-01-04T11","id":"18y0irm","position":53,"score":4124,"subreddit_display_name":"AskReddit","subreddit_id":"2qh1i","title":"What hobby is an instant red flag?","is_self":1,"url":"https://www.reddit.com/r/AskReddit/comments/18y0irm/what_hobby_is_an_instant_red_flag/","upvote_ratio":0.92000000000000003996,"num_comments":4181,"created":1704331942,"created_date":"2024-01-04T01:32:22+0000"},
{"date":"2024-01-04T11","id":"18y0c3m","position":28,"score":9495,"subreddit_display_name":"shitposting","subreddit_id":"2usxq","title":"epstein shid himself","is_self":0,"url":"https://v.redd.it/j7ed6gvesbac1","upvote_ratio":0.94999999999999995559,"num_comments":240,"created":1704331447,"created_date":"2024-01-04T01:24:07+0000"},
{"date":"2024-01-04T11","id":"18y0b39","position":65,"score":3998,"subreddit_display_name":"technicallythetruth","subreddit_id":"3pzez","title":"No, she's got the Point","is_self":0,"url":"https://i.redd.it/7ugu3un5sbac1.png","upvote_ratio":0.95999999999999996447,"num_comments":48,"created":1704331370,"created_date":"2024-01-04T01:22:50+0000"},
{"date":"2024-01-04T11","id":"18y0b0d","position":20,"score":9338,"subreddit_display_name":"BlackPeopleTwitter","subreddit_id":"33x33","title":"Man was movin like Polamalu","is_self":0,"url":"https://v.redd.it/rhxvqtr5sbac1","upvote_ratio":0.9399999999999999467,"num_comments":580,"created":1704331364,"created_date":"2024-01-04T01:22:44+0000"},
{"date":"2024-01-04T11","id":"18y04ar","position":49,"score":4732,"subreddit_display_name":"BaldursGate3","subreddit_id":"12967t","title":"It's tough being the protagonist","is_self":0,"url":"https://i.redd.it/989j244mqbac1.jpeg","upvote_ratio":0.9399999999999999467,"num_comments":203,"created":1704330874,"created_date":"2024-01-04T01:14:34+0000"},
{"date":"2024-01-04T11","id":"18xzzni","position":45,"score":28655,"subreddit_display_name":"Damnthatsinteresting","subreddit_id":"2xxyj","title":"How to make lipstick (2000 years ago)","is_self":0,"url":"https://v.redd.it/asy2bptjpbac1","upvote_ratio":0.89000000000000001332,"num_comments":1060,"created":1704330534,"created_date":"2024-01-04T01:08:54+0000"},
{"date":"2024-01-04T11","id":"18xzzjq","position":19,"score":11362,"subreddit_display_name":"ContagiousLaughter","subreddit_id":"2u2bh","title":"Drill Sergeant Daddy","is_self":0,"url":"https://v.redd.it/g2bv4nahpbac1","upvote_ratio":0.9399999999999999467,"num_comments":284,"created":1704330526,"created_date":"2024-01-04T01:08:46+0000"},
{"date":"2024-01-04T11","id":"18xzu86","position":25,"score":7512,"subreddit_display_name":"politics","subreddit_id":"2cneq","title":"Clinton and Trump are named in Jeffrey Epstein documents, no wrongdoing alleged","is_self":0,"url":"https://www.usatoday.com/story/news/politics/2024/01/03/jeffrey-epstein-list-clinton-trump/72086945007/","upvote_ratio":0.9399999999999999467,"num_comments":1423,"created":1704330129,"created_date":"2024-01-04T01:02:09+0000"},
{"date":"2024-01-04T11","id":"18xzg5o","position":79,"score":3831,"subreddit_display_name":"worldnews","subreddit_id":"2qh13","title":"Hezbollah confirms: Senior member of the organization killed in Israeli strike","is_self":0,"url":"https://www.israelnationalnews.com/news/383037","upvote_ratio":0.93000000000000004884,"num_comments":366,"created":1704329125,"created_date":"2024-01-04T12:45:25+0000"},
{"date":"2024-01-04T11","id":"18xzfk8","position":59,"score":4525,"subreddit_display_name":"gifs","subreddit_id":"2qt55","title":"Automatic Candle Extinguisher from 1841","is_self":0,"url":"https://i.imgur.com/LwWYEaJ.gifv","upvote_ratio":0.93000000000000004884,"num_comments":112,"created":1704329087,"created_date":"2024-01-04T12:44:47+0000"},
{"date":"2024-01-04T11","id":"18xze67","position":39,"score":31991,"subreddit_display_name":"MadeMeSmile","subreddit_id":"2uqcm","title":"Winning! Final hematologist appointment, cancer free! Acute Myeloid Leukemia in remission, cheers with me.","is_self":0,"url":"https://i.redd.it/1f6qdhr3lbac1.jpeg","upvote_ratio":0.94999999999999995559,"num_comments":599,"created":1704328985,"created_date":"2024-01-04T12:43:05+0000"},
{"date":"2024-01-04T11","id":"18xz2wm","position":95,"score":3555,"subreddit_display_name":"nope","subreddit_id":"2s5fh","title":"Man attacks judge after she refused to give him probation","is_self":0,"url":"https://v.redd.it/zol0i61mibac1","upvote_ratio":0.93000000000000004884,"num_comments":338,"created":1704328176,"created_date":"2024-01-04T12:29:36+0000"},
{"date":"2024-01-04T11","id":"18xyyma","position":96,"score":3480,"subreddit_display_name":"chaoticgood","subreddit_id":"2qjo5","title":"Texas coffee shop under fire for providing Plan B through Jane’s Due Process","is_self":0,"url":"https://i.redd.it/7g04whdrhbac1.jpeg","upvote_ratio":0.96999999999999997335,"num_comments":87,"created":1704327865,"created_date":"2024-01-04T12:24:25+0000"},
{"date":"2024-01-04T11","id":"18xyvrx","position":85,"score":4123,"subreddit_display_name":"FUCKYOUINPARTICULAR","subreddit_id":"3538a","title":"From r/foundsatan 😶","is_self":0,"url":"https://i.redd.it/we6prpa6hbac1.jpeg","upvote_ratio":0.93000000000000004884,"num_comments":280,"created":1704327664,"created_date":"2024-01-04T12:21:04+0000"},
{"date":"2024-01-04T11","id":"18xykou","position":71,"score":5033,"subreddit_display_name":"TopCharacterDesigns","subreddit_id":"86ohyi","title":"West of Loathing Concept Art vs In-Game:","is_self":0,"url":"https://www.reddit.com/gallery/18xykou","upvote_ratio":0.94999999999999995559,"num_comments":97,"created":1704326873,"created_date":"2024-01-04T12:07:53+0000"},
{"date":"2024-01-04T11","id":"18xykgz","position":51,"score":6408,"subreddit_display_name":"perfectlycutscreams","subreddit_id":"3n7fs","title":"the best one I've seen","is_self":0,"url":"https://v.redd.it/xpst531sebac1","upvote_ratio":0.9000000000000000222,"num_comments":60,"created":1704326858,"created_date":"2024-01-04T12:07:38+0000"},
{"date":"2024-01-04T11","id":"18xy6fb","position":48,"score":6878,"subreddit_display_name":"PrequelMemes","subreddit_id":"3i60n","title":"The truth was out there","is_self":0,"url":"https://v.redd.it/ig62pijnbbac1","upvote_ratio":0.96999999999999997335,"num_comments":47,"created":1704325879,"created_date":"2024-01-03T11:51:19+0000"},
{"date":"2024-01-04T11","id":"18xxryv","position":62,"score":5674,"subreddit_display_name":"cats","subreddit_id":"2qhta","title":"Wife kept saying my snoring was waking her up but as it turns out….","is_self":0,"url":"https://v.redd.it/5vd5ck4y8bac1","upvote_ratio":0.98999999999999999111,"num_comments":85,"created":1704324898,"created_date":"2024-01-03T11:34:58+0000"},
{"date":"2024-01-04T11","id":"18xxkam","position":44,"score":9160,"subreddit_display_name":"rareinsults","subreddit_id":"48t85","title":"Cute- 😍😍 Not cute- ☹️☹️","is_self":0,"url":"https://i.redd.it/ra7998je7bac1.jpeg","upvote_ratio":0.94999999999999995559,"num_comments":112,"created":1704324378,"created_date":"2024-01-03T11:26:18+0000"},
{"date":"2024-01-04T11","id":"18xxgy3","position":47,"score":7736,"subreddit_display_name":"KidsAreFuckingStupid","subreddit_id":"3948y","title":"He did not care one bit","is_self":0,"url":"https://v.redd.it/bpzvgolp6bac1","upvote_ratio":0.92000000000000003996,"num_comments":417,"created":1704324144,"created_date":"2024-01-03T11:22:24+0000"},
{"date":"2024-01-04T11","id":"18xxgk2","position":61,"score":5997,"subreddit_display_name":"AbruptChaos","subreddit_id":"3nasz","title":"A judge in Las Vegas is attacked during a live hearing after she denied probation","is_self":0,"url":"https://v.redd.it/g20it3wm6bac1","upvote_ratio":0.9399999999999999467,"num_comments":995,"created":1704324119,"created_date":"2024-01-03T11:21:59+0000"},
{"date":"2024-01-04T11","id":"18xxfgu","position":97,"score":4788,"subreddit_display_name":"Deltarune","subreddit_id":"qmi8w","title":"think about it","is_self":0,"url":"https://i.redd.it/dsb469zd6bac1.png","upvote_ratio":0.95999999999999996447,"num_comments":102,"created":1704324044,"created_date":"2024-01-03T11:20:44+0000"},
{"date":"2024-01-04T11","id":"18xx8kh","position":91,"score":4519,"subreddit_display_name":"blackcats","subreddit_id":"2twpw","title":"Everyone congratulate my house panther on her SOCK KILL","is_self":0,"url":"https://i.redd.it/2x8mdmj05bac1.png","upvote_ratio":0.96999999999999997335,"num_comments":90,"created":1704323574,"created_date":"2024-01-03T11:12:54+0000"},
{"date":"2024-01-04T11","id":"18xx4un","position":77,"score":16384,"subreddit_display_name":"todayilearned","subreddit_id":"2qqjc","title":"TIL: Short Sleeper Syndrome is a gene mutation discovered by the University of Pittsburgh in 2014. They can function normally with less than 6 hours of sleep and never need to \"recover\" from lack of sleep as opposed to people who purposefully limit sleep. The mutation was given to mice and worked.","is_self":0,"url":"https://www.healthline.com/health/sleep/natural-short-sleeper","upvote_ratio":0.95999999999999996447,"num_comments":1099,"created":1704323332,"created_date":"2024-01-03T11:08:52+0000"},
{"date":"2024-01-04T11","id":"18xx0vg","position":37,"score":10505,"subreddit_display_name":"lego","subreddit_id":"2qhm7","title":"I made a brass armor for Lego","is_self":0,"url":"https://www.reddit.com/gallery/18xx0vg","upvote_ratio":0.97999999999999998223,"num_comments":240,"created":1704323060,"created_date":"2024-01-03T11:04:20+0000"},
{"date":"2024-01-04T11","id":"18xx084","position":93,"score":4593,"subreddit_display_name":"CatDistributionSystem","subreddit_id":"7l5bxn","title":"We stopped at a gas station and got back in car to find this lad in the backseat.","is_self":0,"url":"https://i.redd.it/2r2i7hpc3bac1.jpeg","upvote_ratio":0.95999999999999996447,"num_comments":181,"created":1704323015,"created_date":"2024-01-03T11:03:35+0000"},
{"date":"2024-01-04T11","id":"18xwz76","position":46,"score":9411,"subreddit_display_name":"oddlysatisfying","subreddit_id":"2x93b","title":"Candle Perfectly Fits Under The Glass","is_self":0,"url":"https://v.redd.it/s3v9pqq43bac1","upvote_ratio":0.83999999999999996891,"num_comments":215,"created":1704322942,"created_date":"2024-01-03T11:02:22+0000"},
{"date":"2024-01-04T11","id":"18xwdo4","position":34,"score":12939,"subreddit_display_name":"pics","subreddit_id":"2qh0u","title":"Black children watching as white children play in a only whites park, 1955","is_self":0,"url":"https://i.redd.it/nwmr2p1wyaac1.jpeg","upvote_ratio":0.9000000000000000222,"num_comments":1073,"created":1704321515,"created_date":"2024-01-03T10:38:35+0000"},
{"date":"2024-01-04T11","id":"18xw9j8","position":78,"score":6445,"subreddit_display_name":"iamatotalpieceofshit","subreddit_id":"3jj03","title":"Man attacks Las Vegas judge during sentencing today","is_self":0,"url":"https://v.redd.it/ibt7lqf0yaac1","upvote_ratio":0.9399999999999999467,"num_comments":1037,"created":1704321233,"created_date":"2024-01-03T10:33:53+0000"},
{"date":"2024-01-04T11","id":"18xvzdn","position":29,"score":35114,"subreddit_display_name":"mildlyinteresting","subreddit_id":"2ti4h","title":"Bubbles in my coffee this morning","is_self":0,"url":"https://i.redd.it/i45ex2nzvaac1.png","upvote_ratio":0.84999999999999997779,"num_comments":2478,"created":1704320541,"created_date":"2024-01-03T10:22:21+0000"},
{"date":"2024-01-04T11","id":"18xvyop","position":24,"score":23580,"subreddit_display_name":"NatureIsFuckingLit","subreddit_id":"3gdh7","title":"🔥 Chimp experiences freedom from a cage for the first time in 28 years 🔥 ","is_self":0,"url":"https://v.redd.it/sqwyz2osvaac1","upvote_ratio":0.94999999999999995559,"num_comments":839,"created":1704320493,"created_date":"2024-01-03T10:21:33+0000"},
{"date":"2024-01-04T11","id":"18xvt2s","position":87,"score":5845,"subreddit_display_name":"MaliciousCompliance","subreddit_id":"3boqz","title":"Boss introduces new timetracking tool to \"avoid time manipulation\", backfires on him","is_self":1,"url":"https://www.reddit.com/r/MaliciousCompliance/comments/18xvt2s/boss_introduces_new_timetracking_tool_to_avoid/","upvote_ratio":0.95999999999999996447,"num_comments":249,"created":1704320117,"created_date":"2024-01-03T10:15:17+0000"},
{"date":"2024-01-04T11","id":"18xvodd","position":80,"score":7184,"subreddit_display_name":"vegaslocals","subreddit_id":"2xdzp","title":"Man Attacks Vegas Judge During Sentencing Today","is_self":0,"url":"https://v.redd.it/7lu5w2qotaac1","upvote_ratio":0.94999999999999995559,"num_comments":1645,"created":1704319804,"created_date":"2024-01-03T10:10:04+0000"},
{"date":"2024-01-04T11","id":"18xvo5t","position":32,"score":23224,"subreddit_display_name":"BeAmazed","subreddit_id":"363r3","title":"Absolute Badass","is_self":0,"url":"https://i.imgur.com/NLABMUv.jpeg","upvote_ratio":0.93000000000000004884,"num_comments":448,"created":1704319789,"created_date":"2024-01-03T10:09:49+0000"},
{"date":"2024-01-04T11","id":"18xvltp","position":41,"score":13834,"subreddit_display_name":"nextfuckinglevel","subreddit_id":"m0bnr","title":"Man reveals the technique that could have been used on Stonehedge","is_self":0,"url":"https://v.redd.it/e33rao0vpaac1","upvote_ratio":0.9399999999999999467,"num_comments":496,"created":1704319633,"created_date":"2024-01-03T10:07:13+0000"},
{"date":"2024-01-04T11","id":"18xvio8","position":27,"score":18843,"subreddit_display_name":"PublicFreakout","subreddit_id":"2yrq6","title":"A Man Attacked a Las Vegas Judge During Sentencing Today","is_self":0,"url":"https://v.redd.it/0klbaupjsaac1","upvote_ratio":0.95999999999999996447,"num_comments":3211,"created":1704319419,"created_date":"2024-01-03T10:03:39+0000"},
{"date":"2024-01-04T11","id":"18xvi7o","position":100,"score":5554,"subreddit_display_name":"holdmycatnip","subreddit_id":"2zhxd","title":"Cat defends itself from attacking cobra!","is_self":0,"url":"https://v.redd.it/ve9l1i1ksaac1","upvote_ratio":0.96999999999999997335,"num_comments":189,"created":1704319386,"created_date":"2024-01-03T10:03:06+0000"},
{"date":"2024-01-04T11","id":"18xvdhi","position":69,"score":9007,"subreddit_display_name":"wizardposting","subreddit_id":"5hjlp1","title":"You fools! You absolute fools!","is_self":0,"url":"https://i.redd.it/7es49kloraac1.jpeg","upvote_ratio":0.95999999999999996447,"num_comments":213,"created":1704319090,"created_date":"2024-01-03T09:58:10+0000"},
{"date":"2024-01-04T11","id":"18xvbu1","position":30,"score":19089,"subreddit_display_name":"interestingasfuck","subreddit_id":"2qhsa","title":"Beachgoers have a close encounter with a Cassowary ","is_self":0,"url":"https://v.redd.it/lyp451lbraac1","upvote_ratio":0.9399999999999999467,"num_comments":2103,"created":1704318974,"created_date":"2024-01-03T09:56:14+0000"},
{"date":"2024-01-04T11","id":"18xvadq","position":72,"score":8287,"subreddit_display_name":"BrandNewSentence","subreddit_id":"mbn0j","title":"Now here's a religion I can understand","is_self":0,"url":"https://i.redd.it/smwfzbwzqaac1.png","upvote_ratio":0.95999999999999996447,"num_comments":276,"created":1704318872,"created_date":"2024-01-03T09:54:32+0000"},
{"date":"2024-01-04T11","id":"18xv6zs","position":31,"score":18958,"subreddit_display_name":"WhitePeopleTwitter","subreddit_id":"35n7t","title":"Oh please do go there! Who wants popcorn?","is_self":0,"url":"https://i.redd.it/ld61kqybqaac1.jpeg","upvote_ratio":0.94999999999999995559,"num_comments":929,"created":1704318638,"created_date":"2024-01-03T09:50:38+0000"},
{"date":"2024-01-04T11","id":"18xuwv0","position":89,"score":8090,"subreddit_display_name":"OnePiece","subreddit_id":"2rfz5","title":"Nico Robin attempt (surprise on 3rd slide) :D","is_self":0,"url":"https://www.reddit.com/gallery/18xuwv0","upvote_ratio":0.81000000000000005329,"num_comments":371,"created":1704317961,"created_date":"2024-01-03T09:39:21+0000"},
{"date":"2024-01-04T11","id":"18xu3p1","position":76,"score":9841,"subreddit_display_name":"FluentInFinance","subreddit_id":"3qpaq8","title":"Should Student Loans be Forgiven like PPP Loans were?","is_self":0,"url":"https://i.redd.it/n1r2tyxdiaac1.png","upvote_ratio":0.88000000000000000444,"num_comments":1099,"created":1704315991,"created_date":"2024-01-03T09:06:31+0000"},
{"date":"2024-01-04T11","id":"18xtyve","position":74,"score":12229,"subreddit_display_name":"clevercomebacks","subreddit_id":"dyqlw","title":"Just like the women he's been with, he never saw this coming","is_self":0,"url":"https://i.redd.it/8k421j5ihaac1.png","upvote_ratio":0.86999999999999999555,"num_comments":771,"created":1704315668,"created_date":"2024-01-03T09:01:08+0000"},
{"date":"2024-01-04T11","id":"18xtxnp","position":81,"score":9012,"subreddit_display_name":"TikTokCringe","subreddit_id":"mvcq5","title":"That's a blessin","is_self":0,"url":"https://v.redd.it/2nlz5br5haac1","upvote_ratio":0.94999999999999995559,"num_comments":208,"created":1704315599,"created_date":"2024-01-03T08:59:59+0000"},
{"date":"2024-01-04T11","id":"18xtga5","position":92,"score":8299,"subreddit_display_name":"gaming","subreddit_id":"2qh03","title":"Jailed Nintendo hacker Gary Bowser denies link to new Switch flash cart","is_self":0,"url":"https://www.videogameschronicle.com/news/jailed-nintendo-hacker-gary-bowser-denies-link-to-new-switch-flash-cart/","upvote_ratio":0.94999999999999995559,"num_comments":492,"created":1704314414,"created_date":"2024-01-03T08:40:14+0000"},
{"date":"2024-01-04T11","id":"18xs90u","position":82,"score":17462,"subreddit_display_name":"SipsTea","subreddit_id":"5tdqj0","title":"But friend shape...","is_self":0,"url":"https://v.redd.it/ertmyfr25aac1","upvote_ratio":0.9000000000000000222,"num_comments":537,"created":1704311488,"created_date":"2024-01-03T07:51:28+0000"},
{"date":"2024-01-04T11","id":"18xqr6r","position":83,"score":20481,"subreddit_display_name":"FunnyAnimals","subreddit_id":"2st2l","title":"Dog thought he was home alone ","is_self":0,"url":"https://v.redd.it/bc2fgd5nu9ac1","upvote_ratio":0.95999999999999996447,"num_comments":173,"created":1704307979,"created_date":"2024-01-03T06:52:59+0000"},
{"date":"2024-01-04T11","id":"18xqr1b","position":64,"score":28293,"subreddit_display_name":"news","subreddit_id":"2qh3l","title":"Names in Jeffrey Epstein court documents to be unsealed in New York on Wednesday","is_self":0,"url":"https://www.cnbc.com/2024/01/03/jeffrey-epstein-court-document-names-unsealed-wednesday-.html","upvote_ratio":0.9399999999999999467,"num_comments":2623,"created":1704307970,"created_date":"2024-01-03T06:52:50+0000"}]
